icf_recommender/__init__.py
icf_recommender/item_collaborative_filtering.py
tests/__init__.py
tests/test_item_collaborative_filtering.py
icf_recommender-0.0.1.dist-info/LICENSE
icf_recommender-0.0.1.dist-info/METADATA
icf_recommender-0.0.1.dist-info/WHEEL
icf_recommender-0.0.1.dist-info/top_level.txt
icf_recommender-0.0.1.dist-info/RECORD
