Metadata-Version: 2.1
Name: icf-recommender
Version: 0.0.1
Summary: Recommendation Algorithm: Item Collaborative Filtering
Home-page: https://github.com/oni-on/item-collaborative-filtering
Author: Oni On
Author-email: oni.on.qepa@gmail.com
License: UNKNOWN
Platform: UNKNOWN
Classifier: Programming Language :: Python :: 3
Classifier: License :: OSI Approved :: GNU Lesser General Public License v3 (LGPLv3)
Classifier: Operating System :: OS Independent
Requires-Python: >=3
Requires-Dist: numpy (==1.15.4)
Requires-Dist: pandas (==0.23.4)
